quick_git_hooks/__init__.py
quick_git_hooks/cli.py
quick_git_hooks/utils.py
quick_git_hooks/templates/.pre-commit-config.yaml
quick_git_hooks/templates/GIT_HOOKS_GUIDE.md
quick_git_hooks/templates/__init__.py
quick_git_hooks/templates/eslint.config.js
quick_git_hooks-0.1.0.dist-info/licenses/LICENSE
quick_git_hooks-0.1.0.dist-info/METADATA
quick_git_hooks-0.1.0.dist-info/WHEEL
quick_git_hooks-0.1.0.dist-info/entry_points.txt
quick_git_hooks-0.1.0.dist-info/top_level.txt
quick_git_hooks-0.1.0.dist-info/RECORD
