Metadata-Version: 2.4
Name: quick_git_hooks
Version: 0.1.0
Summary: A CLI tool to quickly set up and check pre-commit Git hooks for Python, JS, and TS projects.
Author-email: "Eng. Elias Owis" <elias@engelias.website>
License: MIT License
Project-URL: Homepage, https://github.com/Eng-Elias/quick-git-hooks
Project-URL: Repository, https://github.com/Eng-Elias/quick-git-hooks
Keywords: git,hooks,pre-commit,linting,formatting,python,javascript,typescript,cli,setup,check
Classifier: Development Status :: 4 - Beta
Classifier: Intended Audience :: Developers
Classifier: License :: OSI Approved :: MIT License
Classifier: Programming Language :: Python :: 3
Classifier: Programming Language :: Python :: 3.7
Classifier: Programming Language :: Python :: 3.8
Classifier: Programming Language :: Python :: 3.9
Classifier: Programming Language :: Python :: 3.10
Classifier: Programming Language :: Python :: 3.11
Classifier: Programming Language :: Python :: 3.12
Classifier: Topic :: Software Development :: Version Control :: Git
Classifier: Topic :: Utilities
Classifier: Environment :: Console
Classifier: Operating System :: OS Independent
Requires-Python: >=3.7
License-File: LICENSE
Requires-Dist: click>=8.0
Requires-Dist: pre-commit>=3.0
Requires-Dist: importlib-resources>=1.3; python_version < "3.9"
Dynamic: license-file
